README.txt
setup.py
caloriegoal/__init__.py
caloriegoal/caloriegoal_properties.py
example_pkg_calorietrackergoal.egg-info/PKG-INFO
example_pkg_calorietrackergoal.egg-info/SOURCES.txt
example_pkg_calorietrackergoal.egg-info/dependency_links.txt
example_pkg_calorietrackergoal.egg-info/top_level.txt